{"put_cargos": [], "cargo_space": {"id": 160820, "mass": 20, "size": {"width": 850, "height": 2100, "length": 1250}, "params": {"protrusion": {"width": 50, "length": 50}, "indentation": {"width": 50, "length": 50}}, "carrying_capacity": 800}, "cargo_groups": [{"mass": 30015, "size": {"width": 380, "height": 103, "length": 600}, "sort": 1, "count": 1, "group_id": "51091033A5", "stacking": true, "turnover": true, "overhang_angle": 50, "stacking_limit": 0, "stacking_is_limited": false}, {"mass": 50703, "size": {"width": 410, "height": 168, "length": 740}, "sort": 2, "count": 1, "group_id": "571839I8", "stacking": true, "turnover": true, "overhang_angle": 50, "stacking_limit": 0, "stacking_is_limited": false}, {"mass": 13045, "size": {"width": 220, "height": 301, "length": 380}, "sort": 3, "count": 1, "group_id": "586891G3", "stacking": true, "turnover": true, "overhang_angle": 50, "stacking_limit": 0, "stacking_is_limited": false}, {"mass": 13045, "size": {"width": 220, "height": 301, "length": 380}, "sort": 4, "count": 4, "group_id": "859499X5", "stacking": true, "turnover": true, "overhang_angle": 50, "stacking_limit": 0, "stacking_is_limited": false}, {"mass": 10696, "size": {"width": 240, "height": 309, "length": 360}, "sort": 5, "count": 1, "group_id": "14410310D6", "stacking": true, "turnover": true, "overhang_angle": 50, "stacking_limit": 0, "stacking_is_limited": false}, {"mass": 14473, "size": {"width": 250, "height": 291, "length": 410}, "sort": 6, "count": 1, "group_id": "542972B1", "stacking": true, "turnover": true, "overhang_angle": 50, "stacking_limit": 0, "stacking_is_limited": false}, {"mass": 14473, "size": {"width": 250, "height": 291, "length": 410}, "sort": 7, "count": 1, "group_id": "688303O0", "stacking": true, "turnover": true, "overhang_angle": 50, "stacking_limit": 0, "stacking_is_limited": false}, {"mass": 14496, "size": {"width": 250, "height": 289, "length": 400}, "sort": 8, "count": 1, "group_id": "1011329Y8", "stacking": true, "turnover": true, "overhang_angle": 50, "stacking_limit": 0, "stacking_is_limited": false}, {"mass": 14524, "size": {"width": 250, "height": 284, "length": 410}, "sort": 9, "count": 1, "group_id": "1937410W9", "stacking": true, "turnover": true, "overhang_angle": 50, "stacking_limit": 0, "stacking_is_limited": false}, {"mass": 9190, "size": {"width": 190, "height": 349, "length": 280}, "sort": 10, "count": 2, "group_id": "724112B0", "stacking": true, "turnover": false, "overhang_angle": 50, "stacking_limit": 0, "stacking_is_limited": false}, {"mass": 5339, "size": {"width": 200, "height": 169, "length": 260}, "sort": 11, "count": 1, "group_id": "261997A5", "stacking": true, "turnover": false, "overhang_angle": 50, "stacking_limit": 0, "stacking_is_limited": false}, {"mass": 9331, "size": {"width": 190, "height": 345, "length": 280}, "sort": 12, "count": 3, "group_id": "864616Z8", "stacking": true, "turnover": true, "overhang_angle": 50, "stacking_limit": 0, "stacking_is_limited": false}, {"mass": 9331, "size": {"width": 190, "height": 345, "length": 280}, "sort": 13, "count": 1, "group_id": "582290F8", "stacking": true, "turnover": true, "overhang_angle": 50, "stacking_limit": 0, "stacking_is_limited": false}, {"mass": 9469, "size": {"width": 190, "height": 345, "length": 270}, "sort": 14, "count": 1, "group_id": "786895C0", "stacking": true, "turnover": true, "overhang_angle": 50, "stacking_limit": 0, "stacking_is_limited": false}, {"mass": 5928, "size": {"width": 200, "height": 172, "length": 270}, "sort": 15, "count": 1, "group_id": "148504W5", "stacking": true, "turnover": false, "overhang_angle": 50, "stacking_limit": 0, "stacking_is_limited": false}, {"mass": 9537, "size": {"width": 180, "height": 325, "length": 270}, "sort": 16, "count": 1, "group_id": "511122Y5", "stacking": true, "turnover": true, "overhang_angle": 50, "stacking_limit": 0, "stacking_is_limited": false}, {"mass": 10999, "size": {"width": 240, "height": 280, "length": 320}, "sort": 17, "count": 1, "group_id": "243352T10", "stacking": true, "turnover": false, "overhang_angle": 50, "stacking_limit": 0, "stacking_is_limited": false}, {"mass": 12573, "size": {"width": 250, "height": 264, "length": 250}, "sort": 18, "count": 1, "group_id": "6786102Z2", "stacking": true, "turnover": true, "overhang_angle": 50, "stacking_limit": 0, "stacking_is_limited": false}, {"mass": 12416, "size": {"width": 200, "height": 218, "length": 370}, "sort": 19, "count": 1, "group_id": "983521B3", "stacking": true, "turnover": true, "overhang_angle": 50, "stacking_limit": 0, "stacking_is_limited": false}, {"mass": 13500, "size": {"width": 210, "height": 300, "length": 300}, "sort": 20, "count": 1, "group_id": "023720S5", "stacking": true, "turnover": true, "overhang_angle": 50, "stacking_limit": 0, "stacking_is_limited": false}, {"mass": 13500, "size": {"width": 210, "height": 300, "length": 300}, "sort": 21, "count": 1, "group_id": "874813D7", "stacking": true, "turnover": true, "overhang_angle": 50, "stacking_limit": 0, "stacking_is_limited": false}, {"mass": 6346, "size": {"width": 170, "height": 248, "length": 230}, "sort": 22, "count": 1, "group_id": "5102209C9", "stacking": true, "turnover": true, "overhang_angle": 50, "stacking_limit": 0, "stacking_is_limited": false}, {"mass": 12781, "size": {"width": 210, "height": 342, "length": 310}, "sort": 23, "count": 1, "group_id": "1011215D5", "stacking": true, "turnover": true, "overhang_angle": 50, "stacking_limit": 0, "stacking_is_limited": false}, {"mass": 12984, "size": {"width": 260, "height": 253, "length": 300}, "sort": 24, "count": 1, "group_id": "516012Y10", "stacking": true, "turnover": true, "overhang_angle": 50, "stacking_limit": 0, "stacking_is_limited": false}, {"mass": 12259, "size": {"width": 190, "height": 200, "length": 360}, "sort": 25, "count": 1, "group_id": "510449H6", "stacking": true, "turnover": true, "overhang_angle": 50, "stacking_limit": 0, "stacking_is_limited": false}, {"mass": 9436, "size": {"width": 190, "height": 351, "length": 280}, "sort": 26, "count": 1, "group_id": "4676210Y8", "stacking": true, "turnover": true, "overhang_angle": 50, "stacking_limit": 0, "stacking_is_limited": false}, {"mass": 6358, "size": {"width": 180, "height": 251, "length": 230}, "sort": 27, "count": 1, "group_id": "622950M1", "stacking": true, "turnover": true, "overhang_angle": 50, "stacking_limit": 0, "stacking_is_limited": false}, {"mass": 5844, "size": {"width": 200, "height": 173, "length": 270}, "sort": 28, "count": 1, "group_id": "75101084A5", "stacking": true, "turnover": false, "overhang_angle": 50, "stacking_limit": 0, "stacking_is_limited": false}, {"mass": 12661, "size": {"width": 200, "height": 344, "length": 320}, "sort": 29, "count": 1, "group_id": "8110828Y0", "stacking": true, "turnover": true, "overhang_angle": 50, "stacking_limit": 0, "stacking_is_limited": false}, {"mass": 12313, "size": {"width": 200, "height": 340, "length": 310}, "sort": 30, "count": 1, "group_id": "153694H5", "stacking": true, "turnover": true, "overhang_angle": 50, "stacking_limit": 0, "stacking_is_limited": false}, {"mass": 12313, "size": {"width": 200, "height": 340, "length": 310}, "sort": 31, "count": 1, "group_id": "554650Z8", "stacking": true, "turnover": true, "overhang_angle": 50, "stacking_limit": 0, "stacking_is_limited": false}, {"mass": 12178, "size": {"width": 200, "height": 332, "length": 310}, "sort": 32, "count": 1, "group_id": "860143J8", "stacking": true, "turnover": true, "overhang_angle": 50, "stacking_limit": 0, "stacking_is_limited": false}, {"mass": 12178, "size": {"width": 200, "height": 332, "length": 310}, "sort": 33, "count": 1, "group_id": "7105600G3", "stacking": true, "turnover": true, "overhang_angle": 50, "stacking_limit": 0, "stacking_is_limited": false}, {"mass": 5844, "size": {"width": 200, "height": 173, "length": 270}, "sort": 34, "count": 1, "group_id": "208077C9", "stacking": true, "turnover": false, "overhang_angle": 50, "stacking_limit": 0, "stacking_is_limited": false}, {"mass": 12586, "size": {"width": 200, "height": 353, "length": 310}, "sort": 35, "count": 1, "group_id": "8102290P5", "stacking": true, "turnover": true, "overhang_angle": 50, "stacking_limit": 0, "stacking_is_limited": false}, {"mass": 12267, "size": {"width": 200, "height": 335, "length": 310}, "sort": 36, "count": 1, "group_id": "9081016T6", "stacking": true, "turnover": true, "overhang_angle": 50, "stacking_limit": 0, "stacking_is_limited": false}, {"mass": 12267, "size": {"width": 200, "height": 335, "length": 310}, "sort": 37, "count": 1, "group_id": "483084J2", "stacking": true, "turnover": true, "overhang_angle": 50, "stacking_limit": 0, "stacking_is_limited": false}, {"mass": 12301, "size": {"width": 200, "height": 336, "length": 310}, "sort": 38, "count": 4, "group_id": "838314R4", "stacking": true, "turnover": true, "overhang_angle": 50, "stacking_limit": 0, "stacking_is_limited": false}, {"mass": 12301, "size": {"width": 200, "height": 336, "length": 310}, "sort": 39, "count": 1, "group_id": "087048Y1", "stacking": true, "turnover": true, "overhang_angle": 50, "stacking_limit": 0, "stacking_is_limited": false}, {"mass": 12246, "size": {"width": 200, "height": 337, "length": 310}, "sort": 40, "count": 1, "group_id": "373459N1", "stacking": true, "turnover": true, "overhang_angle": 50, "stacking_limit": 0, "stacking_is_limited": false}, {"mass": 6399, "size": {"width": 200, "height": 241, "length": 260}, "sort": 41, "count": 1, "group_id": "091293T7", "stacking": true, "turnover": true, "overhang_angle": 50, "stacking_limit": 0, "stacking_is_limited": false}, {"mass": 9406, "size": {"width": 190, "height": 338, "length": 260}, "sort": 42, "count": 1, "group_id": "41101015T8", "stacking": true, "turnover": true, "overhang_angle": 50, "stacking_limit": 0, "stacking_is_limited": false}, {"mass": 9406, "size": {"width": 190, "height": 338, "length": 260}, "sort": 43, "count": 1, "group_id": "7545109C0", "stacking": true, "turnover": true, "overhang_angle": 50, "stacking_limit": 0, "stacking_is_limited": false}, {"mass": 9328, "size": {"width": 180, "height": 331, "length": 260}, "sort": 44, "count": 1, "group_id": "302743X4", "stacking": true, "turnover": true, "overhang_angle": 50, "stacking_limit": 0, "stacking_is_limited": false}, {"mass": 12826, "size": {"width": 200, "height": 342, "length": 310}, "sort": 45, "count": 1, "group_id": "309208Q0", "stacking": true, "turnover": true, "overhang_angle": 50, "stacking_limit": 0, "stacking_is_limited": false}, {"mass": 9384, "size": {"width": 180, "height": 342, "length": 270}, "sort": 46, "count": 1, "group_id": "6310864K8", "stacking": true, "turnover": true, "overhang_angle": 50, "stacking_limit": 0, "stacking_is_limited": false}, {"mass": 9304, "size": {"width": 180, "height": 337, "length": 270}, "sort": 47, "count": 2, "group_id": "988888U8", "stacking": true, "turnover": true, "overhang_angle": 50, "stacking_limit": 0, "stacking_is_limited": false}, {"mass": 9537, "size": {"width": 200, "height": 324, "length": 290}, "sort": 48, "count": 1, "group_id": "050266W8", "stacking": true, "turnover": true, "overhang_angle": 50, "stacking_limit": 0, "stacking_is_limited": false}, {"mass": 3480, "size": {"width": 220, "height": 164, "length": 360}, "sort": 49, "count": 1, "group_id": "504924E1", "stacking": true, "turnover": false, "overhang_angle": 50, "stacking_limit": 0, "stacking_is_limited": false}, {"mass": 1165, "size": {"width": 160, "height": 133, "length": 360}, "sort": 50, "count": 1, "group_id": "10947103S10", "stacking": true, "turnover": false, "overhang_angle": 50, "stacking_limit": 0, "stacking_is_limited": false}, {"mass": 3057, "size": {"width": 200, "height": 166, "length": 410}, "sort": 51, "count": 1, "group_id": "096337G1", "stacking": true, "turnover": false, "overhang_angle": 50, "stacking_limit": 0, "stacking_is_limited": false}, {"mass": 799, "size": {"width": 90, "height": 70, "length": 150}, "sort": 52, "count": 1, "group_id": "546638G4", "stacking": true, "turnover": false, "overhang_angle": 50, "stacking_limit": 0, "stacking_is_limited": false}, {"mass": 1899, "size": {"width": 170, "height": 80, "length": 180}, "sort": 53, "count": 1, "group_id": "537503B4", "stacking": true, "turnover": false, "overhang_angle": 50, "stacking_limit": 0, "stacking_is_limited": false}, {"mass": 1716, "size": {"width": 160, "height": 90, "length": 180}, "sort": 54, "count": 1, "group_id": "680460V9", "stacking": true, "turnover": false, "overhang_angle": 50, "stacking_limit": 0, "stacking_is_limited": false}, {"mass": 596, "size": {"width": 90, "height": 60, "length": 170}, "sort": 55, "count": 1, "group_id": "854477P0", "stacking": true, "turnover": false, "overhang_angle": 50, "stacking_limit": 0, "stacking_is_limited": false}, {"mass": 2547, "size": {"width": 300, "height": 140, "length": 550}, "sort": 56, "count": 1, "group_id": "4104600U4", "stacking": true, "turnover": false, "overhang_angle": 50, "stacking_limit": 0, "stacking_is_limited": false}, {"mass": 2352, "size": {"width": 100, "height": 210, "length": 250}, "sort": 57, "count": 1, "group_id": "975621V0", "stacking": true, "turnover": false, "overhang_angle": 50, "stacking_limit": 0, "stacking_is_limited": false}, {"mass": 363, "size": {"width": 80, "height": 160, "length": 110}, "sort": 58, "count": 1, "group_id": "411121K2", "stacking": true, "turnover": false, "overhang_angle": 50, "stacking_limit": 0, "stacking_is_limited": false}, {"mass": 1200, "size": {"width": 290, "height": 190, "length": 400}, "sort": 59, "count": 1, "group_id": "010410910W2", "stacking": true, "turnover": false, "overhang_angle": 50, "stacking_limit": 0, "stacking_is_limited": false}, {"mass": 1496, "size": {"width": 295, "height": 250, "length": 385}, "sort": 60, "count": 1, "group_id": "113874L10", "stacking": true, "turnover": false, "overhang_angle": 50, "stacking_limit": 0, "stacking_is_limited": false}, {"mass": 5126, "size": {"width": 420, "height": 181, "length": 590}, "sort": 61, "count": 1, "group_id": "531755Z6", "stacking": true, "turnover": false, "overhang_angle": 50, "stacking_limit": 0, "stacking_is_limited": false}, {"mass": 464, "size": {"width": 380, "height": 233, "length": 430}, "sort": 62, "count": 1, "group_id": "345659K5", "stacking": true, "turnover": false, "overhang_angle": 50, "stacking_limit": 0, "stacking_is_limited": false}, {"mass": 2962, "size": {"width": 200, "height": 104, "length": 260}, "sort": 63, "count": 1, "group_id": "8910382W10", "stacking": true, "turnover": false, "overhang_angle": 50, "stacking_limit": 0, "stacking_is_limited": false}, {"mass": 1536, "size": {"width": 295, "height": 250, "length": 385}, "sort": 64, "count": 1, "group_id": "598804O3", "stacking": true, "turnover": false, "overhang_angle": 50, "stacking_limit": 0, "stacking_is_limited": false}, {"mass": 1536, "size": {"width": 295, "height": 250, "length": 385}, "sort": 65, "count": 1, "group_id": "403157U10", "stacking": true, "turnover": false, "overhang_angle": 50, "stacking_limit": 0, "stacking_is_limited": false}, {"mass": 2010, "size": {"width": 410, "height": 252, "length": 440}, "sort": 66, "count": 1, "group_id": "1069845U0", "stacking": true, "turnover": false, "overhang_angle": 50, "stacking_limit": 0, "stacking_is_limited": false}, {"mass": 4901, "size": {"width": 230, "height": 209, "length": 420}, "sort": 67, "count": 1, "group_id": "7610762M10", "stacking": true, "turnover": false, "overhang_angle": 50, "stacking_limit": 0, "stacking_is_limited": false}, {"mass": 3230, "size": {"width": 380, "height": 196, "length": 620}, "sort": 68, "count": 1, "group_id": "032579A3", "stacking": true, "turnover": false, "overhang_angle": 50, "stacking_limit": 0, "stacking_is_limited": false}, {"mass": 3230, "size": {"width": 380, "height": 196, "length": 620}, "sort": 69, "count": 1, "group_id": "6791038L9", "stacking": true, "turnover": false, "overhang_angle": 50, "stacking_limit": 0, "stacking_is_limited": false}, {"mass": 3494, "size": {"width": 390, "height": 233, "length": 750}, "sort": 70, "count": 1, "group_id": "1063678H9", "stacking": true, "turnover": false, "overhang_angle": 50, "stacking_limit": 0, "stacking_is_limited": false}, {"mass": 3494, "size": {"width": 390, "height": 233, "length": 750}, "sort": 71, "count": 1, "group_id": "851416B2", "stacking": true, "turnover": false, "overhang_angle": 50, "stacking_limit": 0, "stacking_is_limited": false}, {"mass": 3231, "size": {"width": 390, "height": 143, "length": 620}, "sort": 72, "count": 2, "group_id": "1047858L6", "stacking": true, "turnover": false, "overhang_angle": 50, "stacking_limit": 0, "stacking_is_limited": false}], "calculation_params": {"packing_side": 0, "calculation_id": 322249, "accounting_center_of_mass": false}}
