{"put_cargos": [], "cargo_space": {"id": 751438, "mass": 20, "size": {"width": 850, "height": 2100, "length": 1250}, "params": {"protrusion": {"width": 50, "length": 50}, "indentation": {"width": 50, "length": 50}}, "carrying_capacity": 500}, "cargo_groups": [{"mass": 3520, "size": {"width": 410, "height": 248, "length": 420}, "sort": 1, "count": 2, "group_id": "4109469X4", "stacking": true, "turnover": false, "overhang_angle": 50, "stacking_limit": 0, "stacking_is_limited": false}, {"mass": 3520, "size": {"width": 410, "height": 248, "length": 420}, "sort": 2, "count": 1, "group_id": "934346H7", "stacking": true, "turnover": false, "overhang_angle": 50, "stacking_limit": 0, "stacking_is_limited": false}, {"mass": 1560, "size": {"width": 170, "height": 200, "length": 370}, "sort": 3, "count": 2, "group_id": "0726109C5", "stacking": true, "turnover": false, "overhang_angle": 50, "stacking_limit": 0, "stacking_is_limited": false}, {"mass": 1865, "size": {"width": 320, "height": 272, "length": 140}, "sort": 4, "count": 1, "group_id": "71010041P3", "stacking": true, "turnover": false, "overhang_angle": 50, "stacking_limit": 0, "stacking_is_limited": false}, {"mass": 4270, "size": {"width": 250, "height": 157, "length": 400}, "sort": 5, "count": 1, "group_id": "152552J0", "stacking": true, "turnover": false, "overhang_angle": 50, "stacking_limit": 0, "stacking_is_limited": false}, {"mass": 4240, "size": {"width": 200, "height": 190, "length": 260}, "sort": 6, "count": 4, "group_id": "174339T3", "stacking": true, "turnover": true, "overhang_angle": 50, "stacking_limit": 0, "stacking_is_limited": false}, {"mass": 2316, "size": {"width": 230, "height": 164, "length": 150}, "sort": 7, "count": 1, "group_id": "390110Z7", "stacking": true, "turnover": false, "overhang_angle": 50, "stacking_limit": 0, "stacking_is_limited": false}, {"mass": 2335, "size": {"width": 160, "height": 159, "length": 210}, "sort": 8, "count": 1, "group_id": "873066O8", "stacking": true, "turnover": false, "overhang_angle": 50, "stacking_limit": 0, "stacking_is_limited": false}, {"mass": 1014, "size": {"width": 180, "height": 170, "length": 370}, "sort": 9, "count": 1, "group_id": "757166Z1", "stacking": true, "turnover": true, "overhang_angle": 50, "stacking_limit": 0, "stacking_is_limited": false}, {"mass": 3367, "size": {"width": 160, "height": 127, "length": 220}, "sort": 10, "count": 1, "group_id": "697684P1", "stacking": true, "turnover": true, "overhang_angle": 50, "stacking_limit": 0, "stacking_is_limited": false}, {"mass": 1272, "size": {"width": 90, "height": 168, "length": 420}, "sort": 11, "count": 1, "group_id": "61011072Y5", "stacking": true, "turnover": false, "overhang_angle": 50, "stacking_limit": 0, "stacking_is_limited": false}, {"mass": 1287, "size": {"width": 80, "height": 167, "length": 420}, "sort": 12, "count": 1, "group_id": "157013V8", "stacking": true, "turnover": true, "overhang_angle": 50, "stacking_limit": 0, "stacking_is_limited": false}, {"mass": 811, "size": {"width": 270, "height": 201, "length": 270}, "sort": 13, "count": 1, "group_id": "598671L8", "stacking": true, "turnover": false, "overhang_angle": 50, "stacking_limit": 0, "stacking_is_limited": false}, {"mass": 811, "size": {"width": 270, "height": 201, "length": 270}, "sort": 14, "count": 1, "group_id": "2284107W3", "stacking": true, "turnover": false, "overhang_angle": 50, "stacking_limit": 0, "stacking_is_limited": false}, {"mass": 2479, "size": {"width": 150, "height": 80, "length": 210}, "sort": 15, "count": 1, "group_id": "731076Z3", "stacking": true, "turnover": true, "overhang_angle": 50, "stacking_limit": 0, "stacking_is_limited": false}, {"mass": 2413, "size": {"width": 200, "height": 280, "length": 310}, "sort": 16, "count": 1, "group_id": "871437G6", "stacking": true, "turnover": false, "overhang_angle": 50, "stacking_limit": 0, "stacking_is_limited": false}, {"mass": 3349, "size": {"width": 160, "height": 128, "length": 220}, "sort": 17, "count": 1, "group_id": "1095926O6", "stacking": true, "turnover": true, "overhang_angle": 50, "stacking_limit": 0, "stacking_is_limited": false}, {"mass": 1465, "size": {"width": 270, "height": 177, "length": 370}, "sort": 18, "count": 1, "group_id": "6510976E10", "stacking": true, "turnover": false, "overhang_angle": 50, "stacking_limit": 0, "stacking_is_limited": false}, {"mass": 3067, "size": {"width": 140, "height": 198, "length": 400}, "sort": 19, "count": 1, "group_id": "10687106A2", "stacking": true, "turnover": false, "overhang_angle": 50, "stacking_limit": 0, "stacking_is_limited": false}, {"mass": 6103, "size": {"width": 170, "height": 133, "length": 370}, "sort": 20, "count": 1, "group_id": "730695L2", "stacking": true, "turnover": true, "overhang_angle": 50, "stacking_limit": 0, "stacking_is_limited": false}, {"mass": 3885, "size": {"width": 140, "height": 197, "length": 400}, "sort": 21, "count": 1, "group_id": "768693O8", "stacking": true, "turnover": false, "overhang_angle": 50, "stacking_limit": 0, "stacking_is_limited": false}, {"mass": 2774, "size": {"width": 300, "height": 126, "length": 400}, "sort": 22, "count": 1, "group_id": "005838X8", "stacking": true, "turnover": false, "overhang_angle": 50, "stacking_limit": 0, "stacking_is_limited": false}, {"mass": 2284, "size": {"width": 220, "height": 110, "length": 130}, "sort": 23, "count": 1, "group_id": "10388107R7", "stacking": true, "turnover": true, "overhang_angle": 50, "stacking_limit": 0, "stacking_is_limited": false}, {"mass": 2284, "size": {"width": 220, "height": 110, "length": 130}, "sort": 24, "count": 1, "group_id": "107237B0", "stacking": true, "turnover": true, "overhang_angle": 50, "stacking_limit": 0, "stacking_is_limited": false}, {"mass": 1272, "size": {"width": 90, "height": 165, "length": 420}, "sort": 25, "count": 1, "group_id": "1005805Y10", "stacking": true, "turnover": true, "overhang_angle": 50, "stacking_limit": 0, "stacking_is_limited": false}, {"mass": 1274, "size": {"width": 80, "height": 167, "length": 420}, "sort": 26, "count": 1, "group_id": "365825N5", "stacking": true, "turnover": true, "overhang_angle": 50, "stacking_limit": 0, "stacking_is_limited": false}, {"mass": 2260, "size": {"width": 220, "height": 114, "length": 120}, "sort": 27, "count": 2, "group_id": "6210108X7", "stacking": true, "turnover": false, "overhang_angle": 50, "stacking_limit": 0, "stacking_is_limited": false}, {"mass": 1260, "size": {"width": 80, "height": 166, "length": 420}, "sort": 28, "count": 1, "group_id": "824518N5", "stacking": true, "turnover": true, "overhang_angle": 50, "stacking_limit": 0, "stacking_is_limited": false}, {"mass": 3963, "size": {"width": 170, "height": 110, "length": 240}, "sort": 29, "count": 1, "group_id": "897314O1", "stacking": true, "turnover": true, "overhang_angle": 50, "stacking_limit": 0, "stacking_is_limited": false}, {"mass": 933, "size": {"width": 210, "height": 251, "length": 310}, "sort": 30, "count": 1, "group_id": "064440X10", "stacking": true, "turnover": false, "overhang_angle": 50, "stacking_limit": 0, "stacking_is_limited": false}, {"mass": 1172, "size": {"width": 90, "height": 163, "length": 430}, "sort": 31, "count": 1, "group_id": "187622M3", "stacking": true, "turnover": false, "overhang_angle": 50, "stacking_limit": 0, "stacking_is_limited": false}, {"mass": 1277, "size": {"width": 80, "height": 167, "length": 430}, "sort": 32, "count": 1, "group_id": "5129610E10", "stacking": true, "turnover": true, "overhang_angle": 50, "stacking_limit": 0, "stacking_is_limited": false}, {"mass": 3357, "size": {"width": 160, "height": 128, "length": 220}, "sort": 33, "count": 1, "group_id": "6710148Q2", "stacking": true, "turnover": true, "overhang_angle": 50, "stacking_limit": 0, "stacking_is_limited": false}, {"mass": 1250, "size": {"width": 90, "height": 169, "length": 430}, "sort": 34, "count": 1, "group_id": "762429X2", "stacking": true, "turnover": true, "overhang_angle": 50, "stacking_limit": 0, "stacking_is_limited": false}, {"mass": 1272, "size": {"width": 90, "height": 165, "length": 420}, "sort": 35, "count": 1, "group_id": "7199105A3", "stacking": true, "turnover": true, "overhang_angle": 50, "stacking_limit": 0, "stacking_is_limited": false}, {"mass": 656, "size": {"width": 130, "height": 117, "length": 150}, "sort": 36, "count": 1, "group_id": "490584R4", "stacking": true, "turnover": false, "overhang_angle": 50, "stacking_limit": 0, "stacking_is_limited": false}, {"mass": 1203, "size": {"width": 150, "height": 124, "length": 390}, "sort": 37, "count": 1, "group_id": "409271B6", "stacking": true, "turnover": false, "overhang_angle": 50, "stacking_limit": 0, "stacking_is_limited": false}, {"mass": 922, "size": {"width": 230, "height": 232, "length": 420}, "sort": 38, "count": 1, "group_id": "9108946K6", "stacking": true, "turnover": false, "overhang_angle": 50, "stacking_limit": 0, "stacking_is_limited": false}, {"mass": 3195, "size": {"width": 270, "height": 197, "length": 370}, "sort": 39, "count": 1, "group_id": "132084C6", "stacking": true, "turnover": false, "overhang_angle": 50, "stacking_limit": 0, "stacking_is_limited": false}, {"mass": 3192, "size": {"width": 270, "height": 196, "length": 370}, "sort": 40, "count": 1, "group_id": "6104473Z10", "stacking": true, "turnover": false, "overhang_angle": 50, "stacking_limit": 0, "stacking_is_limited": false}, {"mass": 2512, "size": {"width": 280, "height": 168, "length": 380}, "sort": 41, "count": 1, "group_id": "452016C5", "stacking": true, "turnover": false, "overhang_angle": 50, "stacking_limit": 0, "stacking_is_limited": false}, {"mass": 2058, "size": {"width": 110, "height": 193, "length": 260}, "sort": 42, "count": 1, "group_id": "667718Y7", "stacking": true, "turnover": false, "overhang_angle": 50, "stacking_limit": 0, "stacking_is_limited": false}, {"mass": 1112, "size": {"width": 230, "height": 231, "length": 250}, "sort": 43, "count": 1, "group_id": "894952Z2", "stacking": true, "turnover": false, "overhang_angle": 50, "stacking_limit": 0, "stacking_is_limited": false}, {"mass": 5137, "size": {"width": 160, "height": 255, "length": 280}, "sort": 44, "count": 1, "group_id": "105410100S1", "stacking": true, "turnover": true, "overhang_angle": 50, "stacking_limit": 0, "stacking_is_limited": false}, {"mass": 1734, "size": {"width": 130, "height": 185, "length": 280}, "sort": 45, "count": 1, "group_id": "7104749L2", "stacking": true, "turnover": false, "overhang_angle": 50, "stacking_limit": 0, "stacking_is_limited": false}, {"mass": 458, "size": {"width": 260, "height": 145, "length": 260}, "sort": 46, "count": 1, "group_id": "685469M7", "stacking": true, "turnover": false, "overhang_angle": 50, "stacking_limit": 0, "stacking_is_limited": false}, {"mass": 2503, "size": {"width": 150, "height": 247, "length": 520}, "sort": 47, "count": 1, "group_id": "458748G4", "stacking": true, "turnover": false, "overhang_angle": 50, "stacking_limit": 0, "stacking_is_limited": false}, {"mass": 1099, "size": {"width": 270, "height": 130, "length": 390}, "sort": 48, "count": 1, "group_id": "982661X5", "stacking": true, "turnover": false, "overhang_angle": 50, "stacking_limit": 0, "stacking_is_limited": false}, {"mass": 1318, "size": {"width": 220, "height": 234, "length": 400}, "sort": 49, "count": 1, "group_id": "4644109N3", "stacking": true, "turnover": false, "overhang_angle": 50, "stacking_limit": 0, "stacking_is_limited": false}, {"mass": 712, "size": {"width": 80, "height": 119, "length": 210}, "sort": 50, "count": 1, "group_id": "488915B8", "stacking": true, "turnover": false, "overhang_angle": 50, "stacking_limit": 0, "stacking_is_limited": false}, {"mass": 664, "size": {"width": 220, "height": 247, "length": 280}, "sort": 51, "count": 1, "group_id": "9610252G7", "stacking": true, "turnover": false, "overhang_angle": 50, "stacking_limit": 0, "stacking_is_limited": false}, {"mass": 799, "size": {"width": 160, "height": 239, "length": 310}, "sort": 52, "count": 1, "group_id": "797373N1", "stacking": true, "turnover": false, "overhang_angle": 50, "stacking_limit": 0, "stacking_is_limited": false}, {"mass": 1021, "size": {"width": 170, "height": 125, "length": 320}, "sort": 53, "count": 1, "group_id": "028355V6", "stacking": true, "turnover": false, "overhang_angle": 50, "stacking_limit": 0, "stacking_is_limited": false}, {"mass": 369, "size": {"width": 250, "height": 143, "length": 270}, "sort": 54, "count": 1, "group_id": "972114Q2", "stacking": true, "turnover": false, "overhang_angle": 50, "stacking_limit": 0, "stacking_is_limited": false}, {"mass": 1317, "size": {"width": 190, "height": 220, "length": 400}, "sort": 55, "count": 1, "group_id": "166239N8", "stacking": true, "turnover": true, "overhang_angle": 50, "stacking_limit": 0, "stacking_is_limited": false}, {"mass": 1189, "size": {"width": 120, "height": 187, "length": 370}, "sort": 56, "count": 1, "group_id": "10910493N6", "stacking": true, "turnover": false, "overhang_angle": 50, "stacking_limit": 0, "stacking_is_limited": false}, {"mass": 1271, "size": {"width": 150, "height": 211, "length": 500}, "sort": 57, "count": 1, "group_id": "731243S6", "stacking": true, "turnover": false, "overhang_angle": 50, "stacking_limit": 0, "stacking_is_limited": false}, {"mass": 1271, "size": {"width": 150, "height": 211, "length": 500}, "sort": 58, "count": 1, "group_id": "260165J3", "stacking": true, "turnover": false, "overhang_angle": 50, "stacking_limit": 0, "stacking_is_limited": false}, {"mass": 1185, "size": {"width": 150, "height": 211, "length": 500}, "sort": 59, "count": 1, "group_id": "3153910J9", "stacking": true, "turnover": false, "overhang_angle": 50, "stacking_limit": 0, "stacking_is_limited": false}, {"mass": 1214, "size": {"width": 140, "height": 193, "length": 330}, "sort": 60, "count": 1, "group_id": "10510956F8", "stacking": true, "turnover": false, "overhang_angle": 50, "stacking_limit": 0, "stacking_is_limited": false}, {"mass": 1110, "size": {"width": 170, "height": 141, "length": 280}, "sort": 61, "count": 1, "group_id": "762627X9", "stacking": true, "turnover": true, "overhang_angle": 50, "stacking_limit": 0, "stacking_is_limited": false}, {"mass": 3003, "size": {"width": 200, "height": 162, "length": 400}, "sort": 62, "count": 1, "group_id": "217667V7", "stacking": true, "turnover": false, "overhang_angle": 50, "stacking_limit": 0, "stacking_is_limited": false}, {"mass": 3003, "size": {"width": 200, "height": 162, "length": 400}, "sort": 63, "count": 1, "group_id": "9699310E9", "stacking": true, "turnover": false, "overhang_angle": 50, "stacking_limit": 0, "stacking_is_limited": false}, {"mass": 854, "size": {"width": 170, "height": 169, "length": 260}, "sort": 64, "count": 1, "group_id": "404685B4", "stacking": true, "turnover": false, "overhang_angle": 50, "stacking_limit": 0, "stacking_is_limited": false}, {"mass": 985, "size": {"width": 140, "height": 103, "length": 230}, "sort": 65, "count": 1, "group_id": "445758L3", "stacking": true, "turnover": false, "overhang_angle": 50, "stacking_limit": 0, "stacking_is_limited": false}, {"mass": 2455, "size": {"width": 240, "height": 148, "length": 330}, "sort": 66, "count": 1, "group_id": "0640710W6", "stacking": true, "turnover": false, "overhang_angle": 50, "stacking_limit": 0, "stacking_is_limited": false}, {"mass": 497, "size": {"width": 120, "height": 197, "length": 130}, "sort": 67, "count": 1, "group_id": "8310575O10", "stacking": true, "turnover": false, "overhang_angle": 50, "stacking_limit": 0, "stacking_is_limited": false}, {"mass": 812, "size": {"width": 110, "height": 146, "length": 330}, "sort": 68, "count": 1, "group_id": "293259E4", "stacking": true, "turnover": false, "overhang_angle": 50, "stacking_limit": 0, "stacking_is_limited": false}, {"mass": 903, "size": {"width": 400, "height": 170, "length": 110}, "sort": 69, "count": 1, "group_id": "78104310O1", "stacking": true, "turnover": false, "overhang_angle": 50, "stacking_limit": 0, "stacking_is_limited": false}, {"mass": 486, "size": {"width": 120, "height": 154, "length": 130}, "sort": 70, "count": 1, "group_id": "4091047Y7", "stacking": true, "turnover": false, "overhang_angle": 50, "stacking_limit": 0, "stacking_is_limited": false}, {"mass": 1339, "size": {"width": 100, "height": 173, "length": 390}, "sort": 71, "count": 1, "group_id": "7108371M3", "stacking": true, "turnover": false, "overhang_angle": 50, "stacking_limit": 0, "stacking_is_limited": false}, {"mass": 903, "size": {"width": 310, "height": 162, "length": 120}, "sort": 72, "count": 1, "group_id": "603509S10", "stacking": true, "turnover": false, "overhang_angle": 50, "stacking_limit": 0, "stacking_is_limited": false}, {"mass": 3044, "size": {"width": 160, "height": 127, "length": 200}, "sort": 73, "count": 1, "group_id": "9710347N10", "stacking": true, "turnover": true, "overhang_angle": 50, "stacking_limit": 0, "stacking_is_limited": false}, {"mass": 2162, "size": {"width": 160, "height": 161, "length": 400}, "sort": 74, "count": 1, "group_id": "839088F1", "stacking": true, "turnover": false, "overhang_angle": 50, "stacking_limit": 0, "stacking_is_limited": false}, {"mass": 1410, "size": {"width": 150, "height": 201, "length": 200}, "sort": 75, "count": 1, "group_id": "597301W2", "stacking": true, "turnover": false, "overhang_angle": 50, "stacking_limit": 0, "stacking_is_limited": false}, {"mass": 474, "size": {"width": 120, "height": 155, "length": 130}, "sort": 76, "count": 1, "group_id": "1006881B9", "stacking": true, "turnover": false, "overhang_angle": 50, "stacking_limit": 0, "stacking_is_limited": false}, {"mass": 2205, "size": {"width": 170, "height": 164, "length": 300}, "sort": 77, "count": 1, "group_id": "154013G3", "stacking": true, "turnover": false, "overhang_angle": 50, "stacking_limit": 0, "stacking_is_limited": false}, {"mass": 4429, "size": {"width": 290, "height": 217, "length": 410}, "sort": 78, "count": 1, "group_id": "769526Y2", "stacking": true, "turnover": false, "overhang_angle": 50, "stacking_limit": 0, "stacking_is_limited": false}, {"mass": 210, "size": {"width": 100, "height": 150, "length": 170}, "sort": 79, "count": 1, "group_id": "5310340U3", "stacking": true, "turnover": false, "overhang_angle": 50, "stacking_limit": 0, "stacking_is_limited": false}, {"mass": 3057, "size": {"width": 200, "height": 166, "length": 410}, "sort": 80, "count": 1, "group_id": "423636R7", "stacking": true, "turnover": false, "overhang_angle": 50, "stacking_limit": 0, "stacking_is_limited": false}, {"mass": 1736, "size": {"width": 220, "height": 108, "length": 280}, "sort": 81, "count": 1, "group_id": "7210895Q5", "stacking": true, "turnover": false, "overhang_angle": 50, "stacking_limit": 0, "stacking_is_limited": false}, {"mass": 1586, "size": {"width": 390, "height": 230, "length": 390}, "sort": 82, "count": 1, "group_id": "064537L2", "stacking": true, "turnover": false, "overhang_angle": 50, "stacking_limit": 0, "stacking_is_limited": false}, {"mass": 613, "size": {"width": 130, "height": 220, "length": 230}, "sort": 83, "count": 1, "group_id": "833146F1", "stacking": true, "turnover": false, "overhang_angle": 50, "stacking_limit": 0, "stacking_is_limited": false}, {"mass": 468, "size": {"width": 130, "height": 40, "length": 150}, "sort": 84, "count": 1, "group_id": "710108108U6", "stacking": true, "turnover": false, "overhang_angle": 50, "stacking_limit": 0, "stacking_is_limited": false}, {"mass": 3079, "size": {"width": 140, "height": 110, "length": 240}, "sort": 85, "count": 1, "group_id": "7130910V8", "stacking": true, "turnover": false, "overhang_angle": 50, "stacking_limit": 0, "stacking_is_limited": false}, {"mass": 1615, "size": {"width": 130, "height": 110, "length": 180}, "sort": 86, "count": 1, "group_id": "877544F4", "stacking": true, "turnover": false, "overhang_angle": 50, "stacking_limit": 0, "stacking_is_limited": false}, {"mass": 1716, "size": {"width": 160, "height": 90, "length": 180}, "sort": 87, "count": 1, "group_id": "7104607B0", "stacking": true, "turnover": false, "overhang_angle": 50, "stacking_limit": 0, "stacking_is_limited": false}, {"mass": 596, "size": {"width": 90, "height": 60, "length": 170}, "sort": 88, "count": 1, "group_id": "175372C8", "stacking": true, "turnover": false, "overhang_angle": 50, "stacking_limit": 0, "stacking_is_limited": false}, {"mass": 596, "size": {"width": 90, "height": 60, "length": 170}, "sort": 89, "count": 1, "group_id": "071676Y4", "stacking": true, "turnover": false, "overhang_angle": 50, "stacking_limit": 0, "stacking_is_limited": false}, {"mass": 267, "size": {"width": 100, "height": 180, "length": 140}, "sort": 90, "count": 1, "group_id": "973344F3", "stacking": true, "turnover": false, "overhang_angle": 50, "stacking_limit": 0, "stacking_is_limited": false}, {"mass": 379, "size": {"width": 130, "height": 90, "length": 190}, "sort": 91, "count": 1, "group_id": "1015481P8", "stacking": true, "turnover": false, "overhang_angle": 50, "stacking_limit": 0, "stacking_is_limited": false}, {"mass": 703, "size": {"width": 300, "height": 230, "length": 350}, "sort": 92, "count": 1, "group_id": "462664P4", "stacking": true, "turnover": false, "overhang_angle": 50, "stacking_limit": 0, "stacking_is_limited": false}, {"mass": 703, "size": {"width": 300, "height": 230, "length": 350}, "sort": 93, "count": 1, "group_id": "758407G7", "stacking": true, "turnover": false, "overhang_angle": 50, "stacking_limit": 0, "stacking_is_limited": false}, {"mass": 588, "size": {"width": 380, "height": 350, "length": 630}, "sort": 94, "count": 1, "group_id": "13109107X3", "stacking": true, "turnover": false, "overhang_angle": 50, "stacking_limit": 0, "stacking_is_limited": false}, {"mass": 608, "size": {"width": 380, "height": 430, "length": 500}, "sort": 95, "count": 1, "group_id": "418763J3", "stacking": true, "turnover": false, "overhang_angle": 50, "stacking_limit": 0, "stacking_is_limited": false}, {"mass": 2668, "size": {"width": 170, "height": 220, "length": 180}, "sort": 96, "count": 1, "group_id": "10210940I1", "stacking": true, "turnover": false, "overhang_angle": 50, "stacking_limit": 0, "stacking_is_limited": false}, {"mass": 448, "size": {"width": 370, "height": 290, "length": 480}, "sort": 97, "count": 1, "group_id": "2089710R3", "stacking": true, "turnover": false, "overhang_angle": 50, "stacking_limit": 0, "stacking_is_limited": false}, {"mass": 450, "size": {"width": 370, "height": 340, "length": 410}, "sort": 98, "count": 1, "group_id": "1070719V6", "stacking": true, "turnover": false, "overhang_angle": 50, "stacking_limit": 0, "stacking_is_limited": false}, {"mass": 629, "size": {"width": 470, "height": 470, "length": 640}, "sort": 99, "count": 1, "group_id": "1064793O7", "stacking": true, "turnover": false, "overhang_angle": 50, "stacking_limit": 0, "stacking_is_limited": false}, {"mass": 439, "size": {"width": 290, "height": 350, "length": 390}, "sort": 100, "count": 1, "group_id": "790477D6", "stacking": true, "turnover": false, "overhang_angle": 50, "stacking_limit": 0, "stacking_is_limited": false}, {"mass": 1146, "size": {"width": 120, "height": 170, "length": 430}, "sort": 101, "count": 1, "group_id": "9319310P9", "stacking": true, "turnover": false, "overhang_angle": 50, "stacking_limit": 0, "stacking_is_limited": false}, {"mass": 424, "size": {"width": 300, "height": 440, "length": 400}, "sort": 102, "count": 1, "group_id": "996014J3", "stacking": true, "turnover": false, "overhang_angle": 50, "stacking_limit": 0, "stacking_is_limited": false}, {"mass": 820, "size": {"width": 120, "height": 110, "length": 190}, "sort": 103, "count": 5, "group_id": "1003001V0", "stacking": true, "turnover": false, "overhang_angle": 50, "stacking_limit": 0, "stacking_is_limited": false}, {"mass": 372, "size": {"width": 340, "height": 480, "length": 570}, "sort": 104, "count": 1, "group_id": "6103057F4", "stacking": true, "turnover": false, "overhang_angle": 50, "stacking_limit": 0, "stacking_is_limited": false}, {"mass": 717, "size": {"width": 120, "height": 60, "length": 130}, "sort": 105, "count": 1, "group_id": "712399N9", "stacking": true, "turnover": false, "overhang_angle": 50, "stacking_limit": 0, "stacking_is_limited": false}, {"mass": 1400, "size": {"width": 230, "height": 180, "length": 240}, "sort": 106, "count": 2, "group_id": "4673010J7", "stacking": true, "turnover": false, "overhang_angle": 50, "stacking_limit": 0, "stacking_is_limited": false}, {"mass": 535, "size": {"width": 80, "height": 190, "length": 290}, "sort": 107, "count": 2, "group_id": "6961064A4", "stacking": true, "turnover": false, "overhang_angle": 50, "stacking_limit": 0, "stacking_is_limited": false}, {"mass": 1518, "size": {"width": 80, "height": 170, "length": 150}, "sort": 108, "count": 1, "group_id": "163075H4", "stacking": true, "turnover": false, "overhang_angle": 50, "stacking_limit": 0, "stacking_is_limited": false}, {"mass": 906, "size": {"width": 800, "height": 350, "length": 820}, "sort": 109, "count": 1, "group_id": "073414Z5", "stacking": true, "turnover": false, "overhang_angle": 50, "stacking_limit": 0, "stacking_is_limited": false}, {"mass": 2964, "size": {"width": 190, "height": 90, "length": 270}, "sort": 110, "count": 1, "group_id": "655085D5", "stacking": true, "turnover": false, "overhang_angle": 50, "stacking_limit": 0, "stacking_is_limited": false}, {"mass": 2189, "size": {"width": 180, "height": 70, "length": 290}, "sort": 111, "count": 1, "group_id": "294154U5", "stacking": true, "turnover": false, "overhang_angle": 50, "stacking_limit": 0, "stacking_is_limited": false}], "calculation_params": {"packing_side": 0, "calculation_id": 732937, "accounting_center_of_mass": false}}
